mentaldistancechecker/__init__.py
mentaldistancechecker/mentaldistancechecker.py
mentaldistancechecker-0.0.1.dist-info/METADATA
mentaldistancechecker-0.0.1.dist-info/WHEEL
mentaldistancechecker-0.0.1.dist-info/top_level.txt
mentaldistancechecker-0.0.1.dist-info/RECORD
