Metadata-Version: 2.1
Name: mentaldistancechecker
Version: 0.0.1
Summary: Estimating mental distance from conversational text and elapsed time.
Home-page: https://ds-musashino-u.github.io/portfolio-pessopeso/
Author: pesonginx
Author-email: s1922011@stu.musashino-u.ac.jp
License: MIT
Keywords: mental mentaldistance mentaldistancechecker
Platform: UNKNOWN
Classifier: License :: OSI Approved :: MIT License
Classifier: Programming Language :: Python :: 3.8
